{"data":[{"number":"3142614327","message":"Convierte en Consultor Natura Digital registrate en https:\/\/bit.ly\/3tLqclg y obten 15% OFF + envio gratis con el cupon PRIMERACOMPRA. V\u00e1lido hasta el 23\/03\/2021","typeLoad":"web","order":"1"},{"number":"3183011111","message":"Convierte en Consultor Natura Digital registrate en https:\/\/bit.ly\/3tLqclg y obten 15% OFF + envio gratis con el cupon PRIMERACOMPRA. V\u00e1lido hasta el 23\/03\/2021","typeLoad":"web","order":"1"}],"path":"","quantitynumbers":"2","note":"PRU","preferences":"20,20,18,8","state":2,"idser":"26","idbase":"953407"}